fews_3di/__init__.py
fews_3di/scripts.py
fews_3di/simulation.py
fews_3di/utils.py
fews_3di/output/log_files_sim_19655.zip
fews_3di/output/log_files_sim_19670.zip
fews_3di/output/log_files_sim_19671.zip
fews_3di/output/log_files_sim_29442.zip
fews_3di/states/3di-cold-state-id.txt
fews_3di/states/3di-saved-state-id.txt
fews_3di/tests/__init__.py
fews_3di/tests/conftest.py
fews_3di/tests/evaporation.nc
fews_3di/tests/example_lateral.csv
fews_3di/tests/example_settings.xml
fews_3di/tests/gridadmin.h5
fews_3di/tests/ow.nc
fews_3di/tests/precipitation.nc
fews_3di/tests/settings_with_old_username.xml
fews_3di/tests/settings_without_api_token.xml
fews_3di/tests/test_scripts.py
fews_3di/tests/test_simulation.py
fews_3di/tests/test_utils.py
fews_3di-3.8.dist-info/LICENSE
fews_3di-3.8.dist-info/METADATA
fews_3di-3.8.dist-info/WHEEL
fews_3di-3.8.dist-info/entry_points.txt
fews_3di-3.8.dist-info/top_level.txt
fews_3di-3.8.dist-info/RECORD
