Metadata-Version: 2.1
Name: fews-3di
Version: 3.8
Summary: FEWS-3Di coupling
Author-email: Reinout van Rees <reinout.vanrees@nelen-schuurmans.nl>
License: The MIT License
Project-URL: Homepage, https://github.com/nens/fews-3di
Project-URL: Changelog, https://github.com/nens/fews-3di/blob/master/CHANGES.rst
Requires-Python: >=3.8
License-File: LICENSE
Requires-Dist: netCDF4
Requires-Dist: pandas
Requires-Dist: requests
Requires-Dist: threedi-api-client>=4.0.1
Requires-Dist: threedigrid
Provides-Extra: test
Requires-Dist: data-science-types; extra == "test"
Requires-Dist: mock; extra == "test"
Requires-Dist: pytest; extra == "test"
Requires-Dist: pytest-mypy; extra == "test"
